axterdb/__init__.py
axterdb/client.py
axterdb/errors.py
axterdb-1.5.dist-info/METADATA
axterdb-1.5.dist-info/WHEEL
axterdb-1.5.dist-info/top_level.txt
axterdb-1.5.dist-info/RECORD
